{
  "indexes": [
    {
      "collectionGroup": "bookings",
      "queryScope": "COLLECTION",
      "fields": [
        {
          "fieldPath": "status",
          "order": "ASCENDING"
        },
        {
          "fieldPath": "slot_datetime",
          "order": "ASCENDING"
        }
      ]
    }
  ],
  "fieldOverrides": [
    {
      "collectionGroup": "turns",
      "fieldPath": "yourFieldName",
      "queryScope": "COLLECTION",
      "fields": [
        {
          "fieldPath": "yourFieldName",
          "order": "ASCENDING"
        }
      ]
    }
  ]
}